ledsign/__init__.py
ledsign/__main__.py
ledsign/backend.py
ledsign/checksum.py
ledsign/device.py
ledsign/hardware.py
ledsign/keypoint_list.py
ledsign/program.py
ledsign/program_io.py
ledsign/protocol.py
ledsign/proxy.py
ledsign-0.8.2.dist-info/licenses/LICENSE.txt
ledsign-0.8.2.dist-info/METADATA
ledsign-0.8.2.dist-info/WHEEL
ledsign-0.8.2.dist-info/top_level.txt
ledsign-0.8.2.dist-info/RECORD
