Metadata-Version: 2.4
Name: ledsign
Version: 0.8.2
Summary: LED Sign Python API
Home-page: https://github.com/krzem5/ledsign
Author: Krzesimir Hyżyk
License: BSD-3-Clause
Project-URL: Source Code, https://github.com/krzem5/ledsign
Project-URL: Documentation, https://ledsign.readthedocs.io/en/latest/
Classifier: Development Status :: 5 - Production/Stable
Classifier: Intended Audience :: End Users/Desktop
Classifier: Natural Language :: English
Classifier: Operating System :: Microsoft :: Windows
Classifier: Operating System :: POSIX :: Linux
Classifier: Programming Language :: Python
Classifier: Programming Language :: Python :: 3.9
Classifier: Programming Language :: Python :: 3.10
Classifier: Programming Language :: Python :: 3.11
Classifier: Programming Language :: Python :: 3.12
Classifier: Programming Language :: Python :: 3.13
Requires-Python: >=3.9
License-File: LICENSE.txt
Dynamic: author
Dynamic: classifier
Dynamic: description
Dynamic: description-content-type
Dynamic: home-page
Dynamic: license
Dynamic: license-file
Dynamic: project-url
Dynamic: requires-python
Dynamic: summary
